{
	"name": "pipeline1",
	"properties": {
		"activities": [
			{
				"name": "Data flow1",
				"type": "ExecuteDataFlow",
				"dependsOn": [],
				"policy": {
					"timeout": "1.00:00:00",
					"retry": 0,
					"retryIntervalInSeconds": 30,
					"secureOutput": false,
					"secureInput": false
				},
				"userProperties": [],
				"typeProperties": {
					"dataflow": {
						"referenceName": "dataflow1",
						"type": "DataFlowReference"
					},
					"compute": {
						"coreCount": 8,
						"computeType": "General"
					},
					"traceLevel": "Fine"
				}
			},
			{
				"name": "Lookup1",
				"type": "Lookup",
				"dependsOn": [
					{
						"activity": "Data flow1",
						"dependencyConditions": [
							"Succeeded"
						]
					}
				],
				"policy": {
					"timeout": "7.00:00:00",
					"retry": 0,
					"retryIntervalInSeconds": 30,
					"secureOutput": false,
					"secureInput": false
				},
				"userProperties": [],
				"typeProperties": {
					"source": {
						"type": "DelimitedTextSource",
						"storeSettings": {
							"type": "AzureBlobStorageReadSettings",
							"recursive": true,
							"wildcardFileName": "*csv",
							"enablePartitionDiscovery": false
						},
						"formatSettings": {
							"type": "DelimitedTextReadSettings"
						}
					},
					"dataset": {
						"referenceName": "ds2_dept",
						"type": "DatasetReference"
					},
					"firstRowOnly": false
				}
			},
			{
				"name": "ForEach1",
				"type": "ForEach",
				"dependsOn": [
					{
						"activity": "Lookup1",
						"dependencyConditions": [
							"Succeeded"
						]
					}
				],
				"userProperties": [],
				"typeProperties": {
					"items": {
						"value": "@activity('Lookup1').output.value",
						"type": "Expression"
					},
					"isSequential": true,
					"activities": [
						{
							"name": "Copy data1",
							"type": "Copy",
							"dependsOn": [],
							"policy": {
								"timeout": "7.00:00:00",
								"retry": 0,
								"retryIntervalInSeconds": 30,
								"secureOutput": false,
								"secureInput": false
							},
							"userProperties": [],
							"typeProperties": {
								"source": {
									"type": "RestSource",
									"httpRequestTimeout": "00:01:40",
									"requestInterval": "00.00:00:00.010",
									"requestMethod": "GET",
									"paginationRules": {
										"supportRFC5988": "true"
									}
								},
								"sink": {
									"type": "AzureSqlSink",
									"tableOption": "autoCreate",
									"disableMetricsCollection": false
								},
								"enableStaging": false,
								"translator": {
									"type": "TabularTranslator",
									"mappings": [
										{
											"source": {
												"path": "$['data']['input_department']"
											},
											"sink": {
												"name": "Basura",
												"type": "String"
											}
										},
										{
											"source": {
												"path": "$['data']['fixed_department']"
											},
											"sink": {
												"name": "Departamento",
												"type": "String"
											}
										}
									],
									"collectionReference": ""
								}
							},
							"inputs": [
								{
									"referenceName": "ds2_api",
									"type": "DatasetReference",
									"parameters": {
										"dept": "@item().Departamento"
									}
								}
							],
							"outputs": [
								{
									"referenceName": "ds2db_departamento",
									"type": "DatasetReference"
								}
							]
						}
					]
				}
			},
			{
				"name": "dataflow2",
				"type": "ExecuteDataFlow",
				"dependsOn": [
					{
						"activity": "ForEach1",
						"dependencyConditions": [
							"Succeeded"
						]
					}
				],
				"policy": {
					"timeout": "1.00:00:00",
					"retry": 0,
					"retryIntervalInSeconds": 30,
					"secureOutput": false,
					"secureInput": false
				},
				"userProperties": [],
				"typeProperties": {
					"dataflow": {
						"referenceName": "dataflow2",
						"type": "DataFlowReference"
					},
					"compute": {
						"coreCount": 8,
						"computeType": "General"
					},
					"traceLevel": "Fine"
				}
			},
			{
				"name": "dataflow3",
				"type": "ExecuteDataFlow",
				"dependsOn": [
					{
						"activity": "dataflow2",
						"dependencyConditions": [
							"Succeeded"
						]
					}
				],
				"policy": {
					"timeout": "1.00:00:00",
					"retry": 0,
					"retryIntervalInSeconds": 30,
					"secureOutput": false,
					"secureInput": false
				},
				"userProperties": [],
				"typeProperties": {
					"dataflow": {
						"referenceName": "dataflow3",
						"type": "DataFlowReference"
					},
					"compute": {
						"coreCount": 8,
						"computeType": "General"
					},
					"traceLevel": "Fine"
				}
			}
		],
		"annotations": [],
		"lastPublishTime": "2021-11-21T02:19:01Z"
	},
	"type": "Microsoft.DataFactory/factories/pipelines"
}